<?xml version="1.0" encoding="UTF-8" ?>
<!--
Licensed to the Apache Software Foundation (ASF) under one
or more contributor license agreements.  See the NOTICE file
distributed with this work for additional information
regarding copyright ownership.  The ASF licenses this file
to you under the Apache License, Version 2.0 (the
"License"); you may not use this file except in compliance
with the License.  You may obtain a copy of the License at

http://www.apache.org/licenses/LICENSE-2.0

Unless required by applicable law or agreed to in writing,
software distributed under the License is distributed on an
"AS IS" BASIS, WITHOUT WARRANTIES OR CONDITIONS OF ANY
KIND, either express or implied.  See the License for the
specific language governing permissions and limitations
under the License.
-->

<simple-methods xmlns:xsi="http://www.w3.org/2001/XMLSchema-instance"
        xsi:noNamespaceSchemaLocation="http://www.ofbiz.org/dtds/simple-methods.xsd">

    <!-- ================================================================ -->
    <!-- ProductCategory Services -->
    <!-- ================================================================ -->

    <simple-method method-name="createProductCategory" short-description="Create an ProductCategory">
        <check-permission permission="CATALOG" action="_CREATE">
            <alt-permission permission="CATALOG_ROLE" action="_CREATE"/>
            <fail-message message="Security Error: to run createProductCategory you must have the CATALOG_CREATE or CATALOG_ADMIN permission, or the limited CATALOG_ROLE_CREATE permission"/>
        </check-permission>
        <check-errors/>

        <now-timestamp-to-env env-name="nowTimestamp"/>
        <make-value value-name="newEntity" entity-name="ProductCategory"/>
        <set-nonpk-fields map-name="parameters" value-name="newEntity"/>

        <if-empty field-name="parameters.productCategoryId">
            <sequenced-id-to-env sequence-name="ProductCategory" env-name="newEntity.productCategoryId"/>
        <else>
            <set field="newEntity.productCategoryId" from-field="parameters.productCategoryId"/>
            <check-id field-name="newEntity.productCategoryId"/>
            <check-errors/>
        </else>
        </if-empty>
        <field-to-result field-name="newEntity.productCategoryId" result-name="productCategoryId"/>
        
        <create-value value-name="newEntity"/>

        <!-- if setting the primaryParentCategoryId, create a rollup entity too -->
        <!-- NOTE: this is commented out to disable because it is dangerous to add category rollups on a live site without being able to specify a fromDate
        <if-not-empty field-name="primaryParentCategoryId" map-name="newEntity">
            <make-value entity-name="ProductCategoryRollup" value-name="newRollup"/>
            <field-to-field field-name="productCategoryId" map-name="newEntity" to-field-name="productCategoryId" to-map-name="newRollup"/>
            <field-to-field field-name="primaryParentCategoryId" map-name="newEntity" to-field-name="parentProductCategoryId" to-map-name="newRollup"/>
            <env-to-field env-name="nowTimestamp" field-name="fromDate" map-name="newRollup"/>
            <create-value value-name="newRollup"/>
        </if-not-empty>
        -->

        <!-- if the user has the role limited position, add this category to the limit category/ies -->
        <if-has-permission permission="CATALOG_ROLE" action="_CREATE">
            <entity-and entity-name="ProductCategoryRole" list-name="productCategoryRoles" filter-by-date="true">
                <field-map field-name="partyId" env-name="userLogin.partyId"/>
                <field-map field-name="roleTypeId" value="LTD_ADMIN"/>
            </entity-and>
            <iterate entry-name="productCategoryRole" list-name="productCategoryRoles">
                <!-- add this new product to the category -->
                <make-value value-name="newLimitRollup" entity-name="ProductCategoryRollup"/>
                <set field="newLimitRollup.productCategoryId" from-field="newEntity.productCategoryId"/>
                <set field="newLimitRollup.parentProductCategoryId" from-field="productCategoryRole.productCategoryId"/>
                <set field="newLimitRollup.fromDate" from-field="nowTimestamp"/>
                <create-value value-name="newLimitRollup"/>
            </iterate>
        </if-has-permission>
    </simple-method>
    <simple-method method-name="updateProductCategory" short-description="Update an ProductCategory">
        <set field="callingMethodName" value="updateProductCategory"/>
        <set field="checkAction" value="UPDATE"/>
        <call-simple-method method-name="checkCategoryRelatedPermission"/>
        <check-errors/>

        <entity-one entity-name="ProductCategory" value-name="lookedUpValue"/>
        <!-- save this value before overwriting it so we can compare it later -->
        <!-- <field-to-field field-name="primaryParentCategoryId" map-name="lookedUpValue" to-map-name="saveIdMap"/> -->
        <set-nonpk-fields map-name="parameters" value-name="lookedUpValue"/>
        <store-value value-name="lookedUpValue"/>

        <!-- if setting the primaryParentCategoryId, create a rollup entity too -->
        <!-- NOTE: this is commented out to disable because it is dangerous to add category rollups on a live site without being able to specify a fromDate
        <if-not-empty field-name="primaryParentCategoryId" map-name="lookedUpValue">
            <if-compare-field field-name="primaryParentCategoryId" map-name="lookedUpValue" operator="not-equals" to-map-name="saveIdMap">
                <make-value entity-name="ProductCategoryRollup" value-name="newRollup"/>
                <field-to-field field-name="productCategoryId" map-name="lookedUpValue" to-field-name="productCategoryId" to-map-name="newRollup"/>
                <field-to-field field-name="primaryParentCategoryId" map-name="lookedUpValue" to-field-name="parentProductCategoryId" to-map-name="newRollup"/>
                <now-timestamp-to-env env-name="nowTimestamp"/>
                <env-to-field env-name="nowTimestamp" field-name="fromDate" map-name="newRollup"/>
                <create-value value-name="newRollup"/>
            </if-compare-field>
        </if-not-empty>
        -->
    </simple-method>

    <!-- ================================================================ -->
    <!-- ProductCategoryMember Services -->
    <!-- ================================================================ -->

    <simple-method method-name="addProductToCategory" short-description="Add Product to Category">
        <!-- note that the security semantics require the user to have the general admin permission,
            or the role limited permission and association with the category, not the product -->
            <!-- 
        <set value="addProductToCategory" field="callingMethodName"/>
        <set value="CREATE" field="checkAction"/>
        <call-simple-method method-name="checkCategoryRelatedPermission"/>
        <check-errors/>
        -->
        <make-value value-name="newEntity" entity-name="ProductCategoryMember"/>
        <set-pk-fields map-name="parameters" value-name="newEntity"/>
        <set-nonpk-fields map-name="parameters" value-name="newEntity"/>

        <if-empty field-name="newEntity.fromDate">
            <now-timestamp-to-env env-name="newEntity.fromDate"/>
        </if-empty>

        <create-value value-name="newEntity"/>
    </simple-method>

    <simple-method method-name="addProductToCategories" short-description="Add Product to Multiple Categories">
        <if-instance-of field-name="parameters.categories" class="java.util.List">
            <iterate entry-name="category" list-name="parameters.categories">
                <!-- note that the security semantics require the user to have the general admin permission,
                    or the role limited permission and association with the category, not the product -->
                <!-- 
                <set field="productCategoryIdToCheck" from-field="category"/>
                <set field="callingMethodName" value="addProductToCategories"/>
                <set field="checkAction" value="CREATE"/>
                <call-simple-method method-name="checkCategoryRelatedPermission"/>
                <check-errors/>
                 -->

                <make-value value-name="newEntity" entity-name="ProductCategoryMember"/>
                <set field="newEntity.productCategoryId" from-field="category"/>
                <set-pk-fields map-name="parameters" value-name="newEntity"/>
                <set-nonpk-fields map-name="parameters" value-name="newEntity"/>

                <if-empty field-name="newEntity.fromDate">
                    <now-timestamp-to-env env-name="newEntity.fromDate"/>
                </if-empty>

                <create-value value-name="newEntity"/>
            </iterate>
            <else>
                <!-- note that the security semantics require the user to have the general admin permission,
                    or the role limited permission and association with the category, not the product -->
                <set from-field="parameters.categories" field="productCategoryIdToCheck"/>
                <set field="callingMethodName" value="addProductToCategories"/>
                <set field="checkAction" value="CREATE"/>
                <call-simple-method method-name="checkCategoryRelatedPermission"/>
                <check-errors/>

                <make-value value-name="newEntity" entity-name="ProductCategoryMember"/>
                <set field="newEntity.productCategoryId" from-field="parameters.categories"/>
                <set-pk-fields map-name="parameters" value-name="newEntity"/>
                <set-nonpk-fields map-name="parameters" value-name="newEntity"/>

                <if-empty field-name="newEntity.fromDate">
                    <now-timestamp-to-env env-name="newEntity.fromDate"/>
                </if-empty>

                <create-value value-name="newEntity"/>
            </else>
        </if-instance-of>
    </simple-method>

    <simple-method method-name="updateProductToCategory" short-description="Update Product to Category Application">
        <!-- note that the security semantics require the user to have the general admin permission,
            or the role limited permission and association with the category, not the product -->
        <!-- 
        <set value="updateProductToCategory" field="callingMethodName"/>
        <set value="UPDATE" field="checkAction"/>
        <call-simple-method method-name="checkCategoryRelatedPermission"/>
        <check-errors/>
         -->

        <make-value value-name="lookupPKMap" entity-name="ProductCategoryMember"/>
        <set-pk-fields map-name="parameters" value-name="lookupPKMap"/>
        <find-by-primary-key entity-name="ProductCategoryMember" map-name="lookupPKMap" value-name="lookedUpValue"/>
        <set-nonpk-fields map-name="parameters" value-name="lookedUpValue"/>
        <store-value value-name="lookedUpValue"/>
    </simple-method>
    <simple-method method-name="removeProductFromCategory" short-description="Remove Product From Category">
        <!-- note that the security semantics require the user to have the general admin permission,
            or the role limited permission and association with the category, not the product -->
        <!-- 
        <set value="removeProductFromCategory" field="callingMethodName"/>
        <set value="DELETE" field="checkAction"/>
        <call-simple-method method-name="checkCategoryRelatedPermission"/>
        <check-errors/>
         -->

        <!-- If the associated category was the primary category for the product, clear that field -->
        <entity-one entity-name="Product" value-name="product" auto-field-map="true"/>
        <if-compare-field field-name="product.primaryProductCategoryId" operator="equals" to-field-name="parameters.productCategoryId">
            <clear-field field-name="product.primaryProductCategoryId"/>
            <store-value value-name="product"/>
        </if-compare-field>

        <make-value value-name="lookupPKMap" entity-name="ProductCategoryMember"/>
        <set-pk-fields map-name="parameters" value-name="lookupPKMap"/>
        <find-by-primary-key entity-name="ProductCategoryMember" map-name="lookupPKMap" value-name="lookedUpValue"/>
        <remove-value value-name="lookedUpValue"/>
    </simple-method>

    <!-- ================================================================ -->
    <!-- ProductCategoryRole Services -->
    <!-- ================================================================ -->

    <simple-method method-name="addPartyToCategory" short-description="Add Party to Category">
        <set value="addPartyToCategory" field="callingMethodName"/>
        <set value="CREATE" field="checkAction"/>
        <call-simple-method method-name="checkCategoryRelatedPermission"/>
        <check-errors/>

        <make-value value-name="newEntity" entity-name="ProductCategoryRole"/>
        <set-pk-fields map-name="parameters" value-name="newEntity"/>
        <set-nonpk-fields map-name="parameters" value-name="newEntity"/>

        <if-empty field-name="newEntity.fromDate">
            <now-timestamp-to-env env-name="newEntity.fromDate"/>
        </if-empty>

        <create-value value-name="newEntity"/>
    </simple-method>
    <simple-method method-name="updatePartyToCategory" short-description="Update Party to Category Application">
        <set value="updatePartyToCategory" field="callingMethodName"/>
        <set value="UPDATE" field="checkAction"/>
        <call-simple-method method-name="checkCategoryRelatedPermission"/>
        <check-errors/>

        <make-value value-name="lookupPKMap" entity-name="ProductCategoryRole"/>
        <set-pk-fields map-name="parameters" value-name="lookupPKMap"/>
        <find-by-primary-key entity-name="ProductCategoryRole" map-name="lookupPKMap" value-name="lookedUpValue"/>
        <set-nonpk-fields map-name="parameters" value-name="lookedUpValue"/>
        <store-value value-name="lookedUpValue"/>
    </simple-method>
    <simple-method method-name="removePartyFromCategory" short-description="Remove Party From Category">
        <set value="removePartyFromCategory" field="callingMethodName"/>
        <set value="DELETE" field="checkAction"/>
        <call-simple-method method-name="checkCategoryRelatedPermission"/>
        <check-errors/>

        <make-value value-name="lookupPKMap" entity-name="ProductCategoryRole"/>
        <set-pk-fields map-name="parameters" value-name="lookupPKMap"/>
        <find-by-primary-key entity-name="ProductCategoryRole" map-name="lookupPKMap" value-name="lookedUpValue"/>
        <remove-value value-name="lookedUpValue"/>
    </simple-method>

    <!-- ================================================================ -->
    <!-- ProductCategoryRollup Services -->
    <!-- ================================================================ -->

    <simple-method method-name="addProductCategoryToCategory" short-description="Add ProductCategory to Category">
        <set value="addProductCategoryToCategory" field="callingMethodName"/>
        <set value="CREATE" field="checkAction"/>
        <!-- note the the user must be associated with the parent category with the role limited permission -->
        <set value="parentProductCategoryId" field="productCategoryIdName"/>
        <call-simple-method method-name="checkCategoryRelatedPermission"/>
        <check-errors/>

        <make-value value-name="newEntity" entity-name="ProductCategoryRollup"/>
        <set-pk-fields map-name="parameters" value-name="newEntity"/>
        <set-nonpk-fields map-name="parameters" value-name="newEntity"/>

        <if-empty field-name="newEntity.fromDate">
            <now-timestamp-to-env env-name="newEntity.fromDate"/>
        </if-empty>

        <create-value value-name="newEntity"/>
    </simple-method>
    <simple-method method-name="addProductCategoryToCategories" short-description="Add ProductCategory to Categories">
        <if-instance-of field-name="parameters.categories" class="java.util.List">
            <iterate entry-name="category" list-name="parameters.categories">
                <set field="callingMethodName" value="addProductCategoryToCategories"/>
                <set field="checkAction" value="CREATE"/>
                <!-- note the the user must be associated with the parent category with the role limited permission -->
                <set field="productCategoryIdToCheck" from-field="category"/>
                <call-simple-method method-name="checkCategoryRelatedPermission"/>
                <check-errors/>

                <make-value value-name="newEntity" entity-name="ProductCategoryRollup"/>
                <set field="newEntity.parentProductCategoryId" from-field="category"/>
                <set-pk-fields map-name="parameters" value-name="newEntity"/>
                <set-nonpk-fields map-name="parameters" value-name="newEntity"/>

                <if-empty field-name="newEntity.fromDate">
                    <now-timestamp-to-env env-name="newEntity.fromDate"/>
                </if-empty>

                <create-value value-name="newEntity"/>
            </iterate>
            <else>
                <set value="addProductCategoryToCategories" field="callingMethodName"/>
                <set value="CREATE" field="checkAction"/>
                <!-- note the the user must be associated with the parent category with the role limited permission -->
                <set field="productCategoryIdToCheck" from-field="parameters.categories"/>                
                <call-simple-method method-name="checkCategoryRelatedPermission"/>
                <check-errors/>

                <make-value value-name="newEntity" entity-name="ProductCategoryRollup"/>
                <set field="newEntity.parentProductCategoryId" from-field="parameters.categories"/>
                <set-pk-fields map-name="parameters" value-name="newEntity"/>
                <set-nonpk-fields map-name="parameters" value-name="newEntity"/>

                <if-empty field-name="newEntity.fromDate">
                    <now-timestamp-to-env env-name="newEntity.fromDate"/>
                </if-empty>

                <create-value value-name="newEntity"/>
            </else>
        </if-instance-of>
    </simple-method>
    <simple-method method-name="updateProductCategoryToCategory" short-description="Update ProductCategory to Category Application">
        <set value="updateProductCategoryToCategory" field="callingMethodName"/>
        <set value="UPDATE" field="checkAction"/>
        <!-- note the the user must be associated with the parent category with the role limited permission -->
        <set value="parentProductCategoryId" field="productCategoryIdName"/>
        <call-simple-method method-name="checkCategoryRelatedPermission"/>
        <check-errors/>

        <make-value value-name="lookupPKMap" entity-name="ProductCategoryRollup"/>
        <set-pk-fields map-name="parameters" value-name="lookupPKMap"/>
        <find-by-primary-key entity-name="ProductCategoryRollup" map-name="lookupPKMap" value-name="lookedUpValue"/>
        <set-nonpk-fields map-name="parameters" value-name="lookedUpValue"/>
        <store-value value-name="lookedUpValue"/>
    </simple-method>
    <simple-method method-name="removeProductCategoryFromCategory" short-description="Remove ProductCategory From Category">
        <set value="removeProductCategoryFromCategory" field="callingMethodName"/>
        <set value="DELETE" field="checkAction"/>
        <!-- note the the user must be associated with the parent category with the role limited permission -->
        <set value="parentProductCategoryId" field="productCategoryIdName"/>
        <call-simple-method method-name="checkCategoryRelatedPermission"/>
        <check-errors/>

        <make-value value-name="lookupPKMap" entity-name="ProductCategoryRollup"/>
        <set-pk-fields map-name="parameters" value-name="lookupPKMap"/>
        <find-by-primary-key entity-name="ProductCategoryRollup" map-name="lookupPKMap" value-name="lookedUpValue"/>
        <remove-value value-name="lookedUpValue"/>
    </simple-method>

    <!-- ================================================================ -->
    <!-- Special Category Function Services -->
    <!-- ================================================================ -->

    <simple-method method-name="copyCategoryProductMembers" short-description="copy CategoryProduct Members to a CategoryProductTo">
        <set value="copyCategoryProductMembers" field="callingMethodName"/>
        <set value="CREATE" field="checkAction"/>
        <!-- note the the user must be associated with the target category with the role limited permission -->
        <set value="productCategoryIdTo" field="productCategoryIdName"/>
        <call-simple-method method-name="checkCategoryRelatedPermission"/>
        <check-errors/>

        <entity-and entity-name="ProductCategoryMember" list-name="productCategoryMembers">
            <field-map field-name="productCategoryId" env-name="parameters.productCategoryId"/>
        </entity-and>

        <set field="validDate" from-field="parameters.validDate"/>
        <if-not-empty field-name="validDate">
            <filter-list-by-date list-name="productCategoryMembers" valid-date-name="validDate"/>
        </if-not-empty>

        <!-- add each to a list to store and then store all and let the entity engine do inserts or updates as needed; much more reliable/useful -->
        <iterate entry-name="productCategoryMember" list-name="productCategoryMembers">
            <clone-value value-name="productCategoryMember" new-value-name="newProductCategoryMember"/>
            <set field="newProductCategoryMember.productCategoryId" from-field="parameters.productCategoryIdTo"/>
            <field-to-list field-name="newProductCategoryMember" list-name="pcmsToStore"/>
        </iterate>
        <store-list list-name="pcmsToStore"/>

        <if-compare field-name="recurse" map-name="parameters" operator="equals" value="Y">
            <!-- call this service for each sub-category in the rollup with the same productCategoryIdTo -->
            <set field="lookupChildrenMap.parentProductCategoryId" from-field="parameters.productCategoryId"/>
            <find-by-and entity-name="ProductCategoryRollup" map-name="lookupChildrenMap" list-name="productCategoryRollups"/>

            <if-not-empty field-name="validDate">
                <filter-list-by-date list-name="productCategoryRollups" valid-date-name="validDate"/>
            </if-not-empty>

            <iterate entry-name="productCategoryRollup" list-name="productCategoryRollups">
                <set field="callServiceMap.productCategoryId" from-field="productCategoryRollup.productCategoryId"/>
                <set field="callServiceMap.productCategoryIdTo" from-field="parameters.productCategoryIdTo"/>
                <set field="callServiceMap.validDate" from-field="parameters.validDate"/>
                <set field="callServiceMap.recurse" from-field="parameters.recurse"/>
                <call-service service-name="copyCategoryProductMembers" in-map-name="callServiceMap"/>
            </iterate>
        </if-compare>
    </simple-method>

    <simple-method method-name="duplicateCategoryEntities" short-description="a service wrapper for copyCategoryEntities">
        <set value="duplicateCategoryEntities" field="callingMethodName"/>
        <check-permission permission="CATALOG" action="_CREATE">
            <alt-permission permission="CATALOG_ROLE" action="_CREATE"/>
            <fail-message message="Security Error: to run createProductCategory you must have the CATALOG_CREATE or CATALOG_ADMIN permission, or the limited CATALOG_ROLE_CREATE permission"/>
        </check-permission>
        <check-errors/>

        <set field="entityName" from-field="parameters.entityName"/>
        <set field="productCategoryId" from-field="parameters.productCategoryId"/>
        <set field="productCategoryIdTo" from-field="parameters.productCategoryIdTo"/>
        <set field="validDate" from-field="parameters.validDate"/>
        <call-simple-method method-name="copyCategoryEntities"/>
    </simple-method>

    <simple-method method-name="copyCategoryEntities" short-description="copies all entities of entityName with a productCategoryId to a new entity with a productCategoryIdTo, 
            filtering them by a timestamp passed in to validDate if necessary">
        <entity-and entity-name="${entityName}" list-name="categoryEntities">
            <field-map field-name="productCategoryId" env-name="productCategoryId"/>
        </entity-and>

        <if-not-empty field-name="validDate">
            <filter-list-by-date list-name="categoryEntities" valid-date-name="validDate"/>
        </if-not-empty>
        
        <!-- add each to a list to store and then store all and let the entity engine do inserts or updates as needed; much more reliable/useful -->
        <iterate entry-name="categoryEntity" list-name="categoryEntities">
            <clone-value value-name="categoryEntity" new-value-name="newCategoryEntity"/>
            <set field="newCategoryEntity.productCategoryId" from-field="productCategoryIdTo"/>
            <field-to-list field-name="newCategoryEntity" list-name="entitiesToStore"/>
        </iterate>
        <store-list list-name="entitiesToStore"/>
      </simple-method>

    <simple-method method-name="expireAllCategoryProductMembers" short-description="Remove ProductCategory From Category">
        <set value="expireAllCategoryProductMembers" field="callingMethodName"/>
        <set value="UPDATE" field="checkAction"/>
        <call-simple-method method-name="checkCategoryRelatedPermission"/>
        <check-errors/>

        <if-not-empty field-name="parameters.thruDate">
            <set field="expireTimestamp" from-field="parameters.thruDate"/>
            <else>
                <now-timestamp-to-env env-name="expireTimestamp"/>
            </else>
        </if-not-empty>

        <entity-and entity-name="ProductCategoryMember" list-name="productCategoryMembers">
            <field-map field-name="productCategoryId" env-name="parameters.productCategoryId"/>
        </entity-and>

        <iterate entry-name="productCategoryMember" list-name="productCategoryMembers">
            <set field="productCategoryMember.thruDate" from-field="expireTimestamp"/>
            <store-value value-name="productCategoryMember"/>
        </iterate>
    </simple-method>
    <simple-method method-name="removeExpiredCategoryProductMembers" short-description="Remove ProductCategory From Category">
        <set value="removeExpiredCategoryProductMembers" field="callingMethodName"/>
        <set value="DELETE" field="checkAction"/>
        <call-simple-method method-name="checkCategoryRelatedPermission"/>
        <check-errors/>

        <if-not-empty field-name="parameters.validDate">
            <set field="expireTimestamp" from-field="parameters.validDate"/>
            <else>
                <now-timestamp-to-env env-name="expireTimestamp"/>
            </else>
        </if-not-empty>

        <entity-and entity-name="ProductCategoryMember" list-name="productCategoryMembers">
            <field-map field-name="productCategoryId" env-name="parameters.productCategoryId"/>
        </entity-and>

        <iterate entry-name="productCategoryMember" list-name="productCategoryMembers">
            <if-compare-field field-name="thruDate" map-name="productCategoryMember" operator="less" to-field-name="expireTimestamp" type="Timestamp">
                <remove-value value-name="productCategoryMember"/>
            </if-compare-field>
        </iterate>
    </simple-method>

    <!-- ================================================================ -->
    <!-- Special Category Related Create Services -->
    <!-- ================================================================ -->
    <simple-method method-name="createProductInCategory" short-description="Create a Product in a Category along with special information such as features">
        <set value="createProductInCategory" field="callingMethodName"/>
        <set value="CREATE" field="checkAction"/>
        <call-simple-method method-name="checkCategoryRelatedPermission"/>
        <check-errors/>

        <if-empty field-name="parameters.currencyUomId">
            <!-- default to USD for lack of a better alternative, for now anyway... -->
            <set field="parameters.currencyUomId" value="USD"/>
        </if-empty>

        <!-- create Product -->
        <set-service-fields service-name="createProduct" map-name="parameters" to-map-name="callCreateProductMap"/>
        <if-empty field-name="callCreateProductMap.productTypeId">
            <set field="callCreateProductMap.productTypeId" value="FINISHED_GOOD"/>
        </if-empty>
        <call-service service-name="createProduct" in-map-name="callCreateProductMap">
            <result-to-field result-name="productId"/>
        </call-service>
        <field-to-result field-name="productId"/>

        <!-- create ProductCategoryMember -->
        <set field="callCreateProductCategoryMemberMap.productId" from-field="productId"/>
        <set field="callCreateProductCategoryMemberMap.productCategoryId" from-field="parameters.productCategoryId"/>
        <call-service service-name="addProductToCategory" in-map-name="callCreateProductCategoryMemberMap"/>

        <!-- create defaultPrice and averageCost ProductPrice -->
        <if-not-empty field-name="parameters.defaultPrice">
            <set field="createDefaultPriceMap.productId" from-field="productId"/>
            <set field="createDefaultPriceMap.currencyUomId" from-field="parameters.currencyUomId"/>
            <set field="createDefaultPriceMap.price" from-field="parameters.defaultPrice"/>
            <set field="createDefaultPriceMap.productStoreGroupId" value="_NA_"/>
            <set field="createDefaultPriceMap.productPriceTypeId" value="DEFAULT_PRICE"/>
            <set field="createDefaultPriceMap.productPricePurposeId" value="PURCHASE"/>
            <call-service service-name="createProductPrice" in-map-name="createDefaultPriceMap"/>
        </if-not-empty>

        <if-not-empty field-name="parameters.averageCost">
            <set field="createAverageCostMap.productId" from-field="productId"/>
            <set field="createAverageCostMap.currencyUomId" from-field="parameters.currencyUomId"/>
            <set field="createAverageCostMap.price" from-field="parameters.averageCost"/>
            <set field="createAverageCostMap.productStoreGroupId" value="_NA_"/>
            <set field="createAverageCostMap.productPriceTypeId" value="AVERAGE_COST"/>
            <set field="createAverageCostMap.productPricePurposeId" value="PURCHASE"/>
            <call-service service-name="createProductPrice" in-map-name="createAverageCostMap"/>
        </if-not-empty>

        <!-- create ProductFeatureAppl(s) -->
        <set field="hasSelectableFeatures" value="N"/>
        <iterate-map map-name="parameters.productFeatureIdByType" key-name="productFeatureTypeId" value-name="productFeatureId">
            <log level="info" message="Applying feature [${productFeatureId}] of type [${productFeatureTypeId}] to product [${productId}]"/>
            <set field="createPfaMap.productId" from-field="productId"/>
            <set field="createPfaMap.productFeatureId" from-field="productFeatureId"/>
            <if-compare field-name="${productFeatureTypeId}" map-name="parameters.productFeatureSelectableByType" operator="equals" value="Y">
                <set field="createPfaMap.productFeatureApplTypeId" value="SELECTABLE_FEATURE"/>
                <set field="hasSelectableFeatures" value="Y"/>
            <else>
                <set field="createPfaMap.productFeatureApplTypeId" value="STANDARD_FEATURE"/>
            </else>
            </if-compare>
            <call-service service-name="applyFeatureToProduct" in-map-name="createPfaMap"/>
            <clear-field field-name="createPfaMap"/>
        </iterate-map>

        <!-- set isVirtual based on hasSelectableFeatures -->
        <if-compare field-name="hasSelectableFeatures" operator="equals" value="Y">
            <entity-one entity-name="Product" value-name="newProduct"/>
            <set field="newProduct.isVirtual" value="Y"/>
            <store-value value-name="newProduct"/>
        </if-compare>
    </simple-method>

    <simple-method method-name="duplicateProductCategory" short-description="Duplicate a ProductCategory">
        <set value="duplicateProductCategory" field="callingMethodName"/>
        <check-permission permission="CATALOG" action="_CREATE">
            <alt-permission permission="CATALOG_ROLE" action="_CREATE"/>
            <fail-message message="Security Error: to run createProductCategory you must have the CATALOG_CREATE or CATALOG_ADMIN permission, or the limited CATALOG_ROLE_CREATE permission"/>
        </check-permission>
        <check-errors/>

        <!-- look up the old product category and clone it -->
        <entity-one entity-name="ProductCategory" value-name="oldCategory">
            <field-map field-name="productCategoryId" env-name="parameters.oldProductCategoryId"/>
        </entity-one>
        <clone-value value-name="oldCategory" new-value-name="newCategory"/>

        <!-- set the new product category id, and write it to the datasource -->
        <set field="newCategory.productCategoryId" from-field="parameters.productCategoryId"/>
        <create-value value-name="newCategory"/>
        <set field="productCategoryId" from-field="parameters.oldProductCategoryId"/>
        <set field="productCategoryIdTo" from-field="parameters.productCategoryId"/>

        <!-- if requested, duplicate related data as well -->
        <if-not-empty field-name="duplicateMembers" map-name="parameters">
            <set field="entityName" value="ProductCategoryMember"/>
            <call-simple-method method-name="copyCategoryEntities"/>
        </if-not-empty>
        <if-not-empty field-name="duplicateContent" map-name="parameters">
            <set field="entityName" value="ProductCategoryContent"/>
            <call-simple-method method-name="copyCategoryEntities"/>
        </if-not-empty>
        <if-not-empty field-name="duplicateRoles" map-name="parameters">
            <set field="entityName" value="ProductCategoryRole"/>
            <call-simple-method method-name="copyCategoryEntities"/>
        </if-not-empty>
        <if-not-empty field-name="duplicateAttributes" map-name="parameters">
            <set field="entityName" value="ProductCategoryAttribute"/>
            <call-simple-method method-name="copyCategoryEntities"/>
        </if-not-empty>
        <if-not-empty field-name="duplicateFeatures" map-name="parameters">
            <set field="entityName" value="ProductFeatureCategoryAppl"/>
            <call-simple-method method-name="copyCategoryEntities"/>
        </if-not-empty>
        <if-not-empty field-name="duplicateCatalogs" map-name="parameters">
            <set field="entityName" value="ProdCatalogCategory"/>
            <call-simple-method method-name="copyCategoryEntities"/>
        </if-not-empty>
 
          <!-- parent rollups are where oldProductCategoryId = ProductCategoryRollup.productCategoryId, but the
            child roll up is where oldProductCategoryId = ProductCategoryRollup.parentProductCategoryId and hence
            requires a new find-by map -->
        <if-not-empty field-name="duplicateParentRollup" map-name="parameters">
            <find-by-and entity-name="ProductCategoryRollup" map-name="categoryFindContext" list-name="foundValues"/>
            <iterate entry-name="foundValue" list-name="foundValues">
                <clone-value value-name="foundValue" new-value-name="newTempValue"/>
                <set field="newTempValue.productCategoryId" from-field="parameters.productCategoryId"/>
                <create-value value-name="newTempValue"/>
            </iterate>
        </if-not-empty>
        <if-not-empty field-name="duplicateChildRollup" map-name="parameters">
            <entity-and entity-name="ProductCategoryRollup" list-name="foundValues">
                <field-map field-name="parentProductCategoryId" env-name="parameters.oldProductCategoryId"/>
            </entity-and>
            <iterate entry-name="foundValue" list-name="foundValues">
                <clone-value value-name="foundValue" new-value-name="newTempValue"/>
                <set field="newTempValue.parentProductCategoryId" from-field="parameters.productCategoryId"/>
                <create-value value-name="newTempValue"/>
            </iterate>
        </if-not-empty>
    </simple-method>

    <!-- ================================================================ -->
    <!-- Product Category Attribute Services -->
    <!-- ================================================================ -->
    
    <simple-method method-name="createProductCategoryAttribute" 
        short-description="Create an attribute for a product category">
        <check-permission permission="CATALOG" action="_CREATE">
            <fail-message message="Security Error: to create a product category attribute requires the CATALOG_CREATE or CATALOG_ADMIN permission"/>
        </check-permission>
        <check-errors/>

        <make-value value-name="newEntity" entity-name="ProductCategoryAttribute"/>
        <set-nonpk-fields map-name="parameters" value-name="newEntity"/>
        <set-pk-fields map-name="parameters" value-name="newEntity"/>
        
        <create-value value-name="newEntity"/>
    </simple-method>
    <simple-method method-name="updateProductCategoryAttribute" 
        short-description="Update an association between two product categories">
        <check-permission permission="CATALOG" action="_UPDATE">
            <fail-message message="Security Error: to update a product category attribute requires the CATALOG_UPDATE or CATALOG_ADMIN permission"/>
          </check-permission>
        <check-errors/>

        <make-value value-name="lookupPKMap" entity-name="ProductCategoryAttribute"/>
        <set-pk-fields map-name="parameters" value-name="lookupPKMap"/>
        <find-by-primary-key entity-name="ProductCategoryAttribute" map-name="lookupPKMap" value-name="ProductCategoryAttributeInstance"/>
        <set-nonpk-fields map-name="parameters" value-name="ProductCategoryAttributeInstance"/>
        <store-value value-name="ProductCategoryAttributeInstance"/>
    </simple-method>
    <simple-method method-name="deleteProductCategoryAttribute" 
        short-description="Delete an association between two product categories">
        <check-permission permission="CATALOG" action="_DELETE">
            <fail-message message="Security Error: to delete a product category attribute requires the CATALOG_DELETE or CATALOG_ADMIN permission"/>
           </check-permission>
        <check-errors/>

        <make-value value-name="lookupPKMap" entity-name="ProductCategoryAttribute"/>
        <set-pk-fields map-name="parameters" value-name="lookupPKMap"/>
        <find-by-primary-key entity-name="ProductCategoryAttribute" map-name="lookupPKMap" value-name="ProductCategoryAttributeInstance"/>
        <remove-value value-name="ProductCategoryAttributeInstance"/>
    </simple-method>
    

    <!-- ProductCategoryLink Create/Update/Delete"-->
    <simple-method method-name="createProductCategoryLink" short-description="create a ProductCategoryLink">
        <make-value entity-name="ProductCategoryLink" value-name="newEntity"/>
        <set field="newEntity.productCategoryId" from-field="parameters.productCategoryId"/>

        <!-- don't set the fromDate yet; let's get the seq ID first -->
        <if-empty field-name="parameters.linkSeqId">
            <make-next-seq-id value-name="newEntity" seq-field-name="linkSeqId"/> <!-- this finds the next sub-sequence ID -->
            <set from-field="linkSeqId" field="newEntity.linkSeqId"/>
        </if-empty>

        <!-- now set the rest of the PK fields (should just be fromDate now; unless linkSeqId is not empty -->
        <set-pk-fields value-name="newEntity" map-name="parameters"/>
        <if-empty field-name="newEntity.fromDate">
            <now-timestamp-to-env env-name="newEntity.fromDate"/>
        </if-empty>

        <set-nonpk-fields map-name="parameters" value-name="newEntity"/>
        <create-value value-name="newEntity"/>  
    </simple-method>   
    
    <simple-method method-name="updateProductCategoryLink" short-description="update a ProductCategoryLink">
        <entity-one entity-name="ProductCategoryLink" value-name="lookedUpValue"/>
        <set-nonpk-fields value-name="lookedUpValue" map-name="parameters"/>
        <store-value value-name="lookedUpValue"/>
    </simple-method>
    
    <simple-method method-name="deleteProductCategoryLink" short-description="delete a ProductCategoryLink">        
        <entity-one entity-name="ProductCategoryLink" value-name="lookedUpValue"/>
        <remove-value value-name="lookedUpValue"/>
    </simple-method>

    <!-- ============================= -->
    <!-- Permission Methods -->
    <!-- ============================= -->
    
    <!-- a methods to centralize product security code, meant to be called in-line with
        call-simple-method, and the checkAction and callingMethodName attributes should be in the method context -->
    <simple-method method-name="checkCategoryRelatedPermission" short-description="Check Product Category Related Permission">
        <if-empty field-name="callingMethodName">
            <set field="callingMethodName" value="this operation"/>
        </if-empty>
        <if-empty field-name="checkAction">
            <set field="checkAction" value="UPDATE"/>
        </if-empty>
        <if-empty field-name="productCategoryIdName">
            <set field="productCategoryIdName" value="productCategoryId"/>
        </if-empty>
        <if-empty field-name="productCategoryIdToCheck">
            <set field="productCategoryIdToCheck" from-field="parameters.${productCategoryIdName}"/>
        </if-empty>
        
        <!-- find all role-categories that this category is a member of -->
        <if>
            <condition>
                <not><if-has-permission permission="CATALOG" action="_${checkAction}"/></not>
            </condition>
            <then>
                <entity-and entity-name="ProductCategoryRollupAndRole" list-name="roleCategories">
                    <field-map field-name="productCategoryId" env-name="productCategoryIdToCheck"/>
                    <field-map field-name="partyId" env-name="userLogin.partyId"/>
                    <field-map field-name="roleTypeId" value="LTD_ADMIN"/>
                </entity-and>
                <filter-list-by-date list-name="roleCategories" valid-date-name="nowTimestamp"/>
                <filter-list-by-date list-name="roleCategories" valid-date-name="nowTimestamp" from-field-name="roleFromDate" thru-field-name="roleThruDate"/>
            </then>
        </if>
        <log level="info" message="Checking category permission, roleCategories=${roleCategories}"/>
        <if>
            <condition>
                <not>
                    <or>
                        <if-has-permission permission="CATALOG" action="_${checkAction}"/>
                        <and>
                            <if-has-permission permission="CATALOG_ROLE" action="_${checkAction}"/>
                            <not><if-empty field-name="roleCategories"/></not>
                        </and>
                    </or>
                </not>
            </condition>
            <then>
                <log level="verbose" message="Permission check failed, user does not have permission"/>
                <add-error><fail-message message="Security Error: to run ${callingMethodName} you must have the CATALOG_${checkAction} or CATALOG_ADMIN permission or have the CATALOG_ROLE_${checkAction} permission and be associated with a category containing this category."/></add-error>
                <set field="hasPermission" type="Boolean" value="false"/>
            </then>
        </if>
    </simple-method>
    <simple-method method-name="productCategoryGenericPermission" short-description="Main permission logic">
        <set field="mainAction" from-field="parameters.mainAction"/>
        <if-empty field-name="mainAction">
            <add-error><fail-message message="In the permission-service element for the productGenericPermission service the main-action attribute was missing but is required"/></add-error>
            <check-errors/>
        </if-empty>
        
        <set field="callingMethodName" from-field="parameters.resourceDescription"/>
        <set field="checkAction" from-field="parameters.mainAction"/>
        <call-simple-method method-name="checkCategoryRelatedPermission"/>
        
        <if-empty field-name="error_list">
            <set field="hasPermission" type="Boolean" value="true"/>
            <field-to-result field-name="hasPermission"/>
            
            <else>
                <property-to-field resource="ProductUiLabels" property="ProductPermissionError" field-name="failMessage"/>
                <set field="hasPermission" type="Boolean" value="false"/>
                <field-to-result field-name="hasPermission"/>
                <field-to-result field-name="failMessage"/>
            </else>
        </if-empty>
    </simple-method>
    
    <!-- a service verion of checkCategoryRelatedPermission, only with purchase/viewAllowPermReqd taken into account -->
    <simple-method method-name="checkCategoryPermissionWithViewPurchaseAllow" short-description="Check Product Category Permission With View and Purchase Allow">
        <set-service-fields service-name="productCategoryGenericPermission" map-name="parameters" to-map-name="productCategoryGenericPermissionMap"/>
        <call-service service-name="productCategoryGenericPermission" in-map-name="productCategoryGenericPermissionMap">
            <results-to-map map-name="genericResult"/>
        </call-service>
        <if-compare field-name="genericResult.hasPermission" operator="equals" value="false" type="Boolean">
            <field-to-result field-name="genericResult.hasPermission" result-name="hasPermission"/>
            <field-to-result field-name="genericResult.failMessage" map-name="failMessage"/>
            <return/>
        </if-compare>
        
        <!-- if the generic permission test passed, carry on -->
        <set field="hasPermission" type="Boolean" value="true"/>
        
        <!--  Set up for a call to checkCategoryRelatedPermission below, but callingMethodName is needed sooner -->
        <set field="callingMethodName" from-field="parameters.resourceDescription" default-value="this operation"/>
        <set field="checkAction" from-field="parameters.mainAction" default-value="UPDATE"/>
        
        <entity-condition list-name="prodCatalogCategoryList" entity-name="ProdCatalogCategory" filter-by-date="true">
            <condition-list combine="and">
                <condition-expr field-name="productCategoryId" env-name="parameters.productCategoryId"/>
                <condition-list combine="or">
                    <condition-expr field-name="prodCatalogCategoryTypeId" value="PCCT_VIEW_ALLW"/>
                    <condition-expr field-name="prodCatalogCategoryTypeId" value="PCCT_PURCH_ALLW"/>
                </condition-list>
            </condition-list>
        </entity-condition>
        <iterate entry-name="prodCatalogCategory" list-name="prodCatalogCategoryList">
            <!-- Do not do a permission check unless the ProdCatalog requires it -->
            <entity-one entity-name="ProdCatalog" value-name="prodCatalog" auto-field-map="false">
                <field-map field-name="prodCatalogId" env-name="prodCatalogCategory.prodCatalogId"/>
            </entity-one>
            <if>
                <condition>
                    <and>
                        <if-compare field-name="prodCatalog.viewAllowPermReqd" operator="equals" value="Y"/>
                        <not><if-has-permission permission="CATALOG_VIEW_ALLOW"/></not>
                    </and>
                </condition>
                <then>
                    <log level="verbose" message="Permission check failed, user does not have permission"/>
                    <set field="failMessage" value="Security Error: to run ${callingMethodName} you must have the CATALOG_VIEW_ALLOW permission."/>
                    <set field="hasPermission" type="Boolean" value="false"/>
                </then>
            </if>
            <if>
                <condition>
                    <and>
                        <if-compare field-name="prodCatalog.purchaseAllowPermReqd" operator="equals" value="Y"/>
                        <not><if-has-permission permission="CATALOG_PURCHASE_ALLOW"/></not>
                    </and>
                </condition>
                <then>
                    <log level="verbose" message="Permission check failed, user does not have permission"/>
                    <set field="failMessage" value="Security Error: to run ${callingMethodName} you must have the CATALOG_PURCHASE_ALLOW permission."/>
                    <set field="hasPermission" type="Boolean" value="false"/>
                </then>
            </if>
        </iterate>
        
        <field-to-result field-name="hasPermission"/>
        <field-to-result field-name="failMessage"/>
    </simple-method>
</simple-methods>
