<?xml version="1.0" encoding="UTF-8"?>
<page>
    <template>main</template>
    <property name="title">Edit Content Purpose Operation</property>
    <property name="headerItem">Admin</property>
    <property name="subMenu">/cms/cms_menu.ftl</property>    
    <property name="formDefFile">/cms/CMSForms.xml</property>
    <property name="entityName">ContentPurposeOperation</property>
    <property name="permission">CONTENTMGR</property>
    <property name="permissionType">simple</property>
    <property name="menuDefFile">/cms/CMSMenus.xml</property>    
    <property name="menuName">cms</property>
    <property name="menuItemName">permissions</property>

    <page-action name="/includes/permprep.bsh" />
    <page-action name="/menu/setcurrentmenuitem.bsh"/>
    <page-action name="/menu/menuinit.bsh"/>
    <content-action name="/includes/crudprep.bsh" />
</page>

